arenaregistration/__init__.py
arenaregistration/affine.py
arenaregistration/points.py
arenaregistration/register.py
arenaregistration/utils.py
build/lib/arenaregistration/__init__.py
build/lib/arenaregistration/affine.py
build/lib/arenaregistration/points.py
build/lib/arenaregistration/register.py
build/lib/arenaregistration/utils.py
imgreg2D/__init__.py
imgreg2D/affine.py
imgreg2D/points.py
imgreg2D/register.py
imgreg2D/utils.py
imgreg2D-0.0.0.2.dist-info/LICENSE
imgreg2D-0.0.0.2.dist-info/METADATA
imgreg2D-0.0.0.2.dist-info/WHEEL
imgreg2D-0.0.0.2.dist-info/top_level.txt
imgreg2D-0.0.0.2.dist-info/RECORD
